.
LICENSE
MANIFEST.in
README.md
requirements.txt
setup.py
/
SnakeSkin.egg-info/PKG-INFO
SnakeSkin.egg-info/SOURCES.txt
SnakeSkin.egg-info/dependency_links.txt
SnakeSkin.egg-info/top_level.txt
bin/snake_skin
snake_skin/__init__.py