Metadata-Version: 1.1
Name: SnakeSkin
Version: 0.0.1
Summary: Python library skeleton tool
Home-page: http://github.com/cadwallion/snake_skin
Author: Andrew Nordman
Author-email: cadwallion@gmail.com
License: UNKNOWN
Platform: UNKNOWN
Classifier: Programming Language :: Python
Classifier: Programming Language :: Python :: 2.7
Classifier: License :: OSI Approved :: MIT License
Classifier: Topic :: Software Development
Classifier: Topic :: Software Development :: Code Generators
Classifier: Topic :: Utilities
